__init__.py
senkalib/__init__.py
senkalib/caaj_journal.py
senkalib/caaj_journal_amount.py
senkalib/caaj_journal_meta.py
senkalib/caaj_journal_side.py
senkalib/caaj_plugin.py
senkalib/senka_lib.py
senkalib/senka_setting.py
senkalib/token_original_id_table.py
senkalib/chain/__init__.py
senkalib/chain/transaction.py
senkalib/chain/transaction_generator.py
senkalib/chain/bsc/__init__.py
senkalib/chain/bsc/bsc_transaction.py
senkalib/chain/bsc/bsc_transaction_generator.py
senkalib/chain/kava/__init__.py
senkalib/chain/kava/kava_transaction.py
senkalib/chain/kava/kava_transaction_generator.py
senkalib/chain/osmosis/__init__.py
senkalib/chain/osmosis/osmosis_transaction.py
senkalib/chain/osmosis/osmosis_transaction_generator.py
senkalib-0.2.4.dist-info/LICENSE
senkalib-0.2.4.dist-info/METADATA
senkalib-0.2.4.dist-info/WHEEL
senkalib-0.2.4.dist-info/top_level.txt
senkalib-0.2.4.dist-info/RECORD
