Metadata-Version: 2.1
Name: senkalib
Version: 0.2.4
Summary: tools for senka
Home-page: https://github.com/ca3-caaip/senkalib
Author: ca3-caaip
Author-email: ywakimoto1s@gmail.com
License: mit
Platform: UNKNOWN
License-File: LICENSE
Requires-Dist: aiohttp (==3.8.1)
Requires-Dist: web3
Requires-Dist: bscscan-python
Requires-Dist: pandas
Provides-Extra: test
Requires-Dist: pytest ; extra == 'test'
Requires-Dist: pytest-cov ; extra == 'test'
